dmlab_maze_generator_cpp.cpython-38-x86_64-linux-gnu.so
dmlab_maze_generator.libs/libgcc_s-a04fdf82.so.1
dmlab_maze_generator.libs/libstdc++-a9383cce.so.6.0.28
dmlab_maze_generator/wrapper.py
dmlab_maze_generator/__init__.py
dmlab_maze_generator-0.1.0.dist-info/WHEEL
dmlab_maze_generator-0.1.0.dist-info/top_level.txt
dmlab_maze_generator-0.1.0.dist-info/METADATA
dmlab_maze_generator-0.1.0.dist-info/LICENSE
dmlab_maze_generator-0.1.0.dist-info/RECORD
