Metadata-Version: 1.2
Name: dmlab-maze-generator
Version: 0.1.0
Summary: Python wrapper for DMLab maze generator
Home-page: https://github.com/jurgisp/dmlab-maze-generator
Author: Jurgis Pasukonis
Author-email: jurgisp@gmail.com
License: UNKNOWN
Platform: UNKNOWN
Requires-Python: >=3.6
